approval/__init__.py
approval/apps.py
approval/settings.py
approval/signals.py
approval/admin/__init__.py
approval/admin/monitored.py
approval/admin/sandbox.py
approval/forms/__init__.py
approval/forms/monitored.py
approval/listeners/__init__.py
approval/listeners/monitored.py
approval/locale/fr/LC_MESSAGES/django.po
approval/models/__init__.py
approval/models/monitored.py
approval/models/monitoring.py
approval/templates/approval/display/sandbox-data.html
approval/templatetags/__init__.py
approval/templatetags/approval.py
django_approval-0.15.1.dist-info/LICENSE
django_approval-0.15.1.dist-info/METADATA
django_approval-0.15.1.dist-info/WHEEL
django_approval-0.15.1.dist-info/top_level.txt
django_approval-0.15.1.dist-info/RECORD
