Metadata-Version: 2.1
Name: django-approval
Version: 0.15.1
Summary: Easily moderate any content in Django before it's visible to the public.
Home-page: https://github.com/artscoop/django-approval
Author: Steve Kossouho
Author-email: skossouho@dawan.fr
License: MIT
Classifier: Programming Language :: Python :: 3
Classifier: License :: OSI Approved :: MIT License
Classifier: Operating System :: OS Independent
Classifier: Framework :: Django
License-File: LICENSE
Requires-Dist: Django >=3.2
Provides-Extra: drf
Requires-Dist: django-rest-framework ; extra == 'drf'
Requires-Dist: rest-framework-generic-relations ; extra == 'drf'
